thelittlethings/__init__.py
thelittlethings/assertion/__init__.py
thelittlethings/assertion/_assertion.py
thelittlethings/auto_reload/__init__.py
thelittlethings/auto_reload/_auto_reload.py
thelittlethings/constants/__init__.py
thelittlethings/constants/_undefined.py
thelittlethings/constants/colors/__init__.py
thelittlethings/constants/colors/_colors.py
thelittlethings/constants/math/__init__.py
thelittlethings/constants/math/_math.py
thelittlethings/debug/__init__.py
thelittlethings/debug/_coloring.py
thelittlethings/debug/_log.py
thelittlethings/debug/_timer.py
thelittlethings/extended_list/__init__.py
thelittlethings/extended_list/_extended_list.py
thelittlethings/files/__init__.py
thelittlethings/files/_files.py
thelittlethings/linked_values/__init__.py
thelittlethings/linked_values/_link.py
thelittlethings/linked_values/_operators.py
thelittlethings/mutable/__init__.py
thelittlethings/mutable/_mutable.py
thelittlethings/progress_bar/__init__.py
thelittlethings/progress_bar/_progress_bar.py
thelittlethings/testing/__init__.py
thelittlethings/testing/_test.py
thelittlethings/to_string/__init__.py
thelittlethings/to_string/_list_to_str.py
thelittlethings/variables/__init__.py
thelittlethings/variables/_get_all_subclasses.py
thelittlethings/variables/_get_first_shared_inheritance.py
thelittlethings/variables/_get_instances.py
thelittlethings/variables/_get_names.py
thelittlethings/variables/_get_types.py
thelittlethings-1.0.8.dist-info/LICENSE
thelittlethings-1.0.8.dist-info/METADATA
thelittlethings-1.0.8.dist-info/WHEEL
thelittlethings-1.0.8.dist-info/top_level.txt
thelittlethings-1.0.8.dist-info/RECORD
