Metadata-Version: 2.1
Name: thelittlethings
Version: 1.0.8
Summary: a library full of small utilities for you to use in your code
Home-page: https://github.com/dots-git/thelittlethings
Author: Simon Kriele
Author-email: kriele.simon@gmail.com
License: UNKNOWN
Project-URL: Bug Tracker, https://github.com/dots-git/thelittlethings/issues
Platform: UNKNOWN
Classifier: Programming Language :: Python :: 3
Classifier: License :: OSI Approved :: GNU General Public License v3 (GPLv3)
Classifier: Operating System :: OS Independent
Requires-Python: >=3.0
License-File: LICENSE
